mytype/__init__.py
mytype-0.0.0.dist-info/LICENSE
mytype-0.0.0.dist-info/METADATA
mytype-0.0.0.dist-info/WHEEL
mytype-0.0.0.dist-info/entry_points.txt
mytype-0.0.0.dist-info/RECORD
